{"pagination":{"object_count":1,"continuation":null,"page_count":1,"page_size":10,"has_more_items":false,"page_number":1},"events":[{"image":{"edge_color_set":true,"edge_color":"#f8980e","url":"https://img.evbuc.com/https%3A%2F%2Fcdn.evbuc.com%2Fimages%2F532135979%2F1596303417783%2F1%2Foriginal.20230608-164607?w=512&auto=format%2Ccompress&q=75&sharp=10&rect=0%2C0%2C6912%2C3456&s=bcf24f613ce14d1432c1763c19b395b2","original":{"url":"https://img.evbuc.com/https%3A%2F%2Fcdn.evbuc.com%2Fimages%2F532135979%2F1596303417783%2F1%2Foriginal.20230608-164607?auto=format%2Ccompress&q=75&sharp=10&s=681caf77834c31f674aa276d67974fcc","width":6912,"height":3456},"crop_mask":{"width":6912,"height":3456,"top_left":{"y":0,"x":0}},"aspect_ratio":"2","id":"532135979"},"saves":{"saved_by_you":false},"event_sales_status":{"start_sales_date":{"timezone":"Asia/Kolkata","local":"2023-06-11T18:00:00","utc":"2023-06-11T12:30:00Z"},"default_message":"Not Yet On Sale","sales_status":"not_yet_on_sale","currency":"USD","message_code":"tickets_not_yet_on_sale","message":"Not Yet On Sale","message_type":"default"},"timezone":"Asia/Kolkata","id":"654073991917","privacy_setting":"unlocked","tickets_by":"Eventbrite","primary_organizer_id":"67027781943","tickets_url":"https://www.eventbrite.com/checkout-external?eid=654073991917","hide_end_date":false,"start_date":"2023-07-25","end_time":"20:00","status":"live","_type":"destination_event","public_collections":{"creator_collections":{"object_count":0,"collections":[]}},"ticket_availability":{"is_sold_out":false,"is_free":true,"minimum_ticket_price":{"currency":"USD","major_value":"0.00","value":0,"display":"0.00 USD"},"has_available_tickets":false,"maximum_ticket_price":{"currency":"USD","major_value":"0.00","value":0,"display":"0.00 USD"}},"end_date":"2023-07-25","tags":[{"prefix":"EventbriteSubCategory","tag":"EventbriteSubCategory/13003","display_name":"City/Town"},{"prefix":"EventbriteCategory","tag":"EventbriteCategory/113","display_name":"Community & Culture","localized":{"display_name":"Community & Culture"}},{"prefix":"EventbriteFormat","tag":"EventbriteFormat/11","display_name":"Party or Social Gathering"},{"_type":"tag","tag":"OrganizerTag/concert","display_name":"concert","prefix":"OrganizerTag"},{"_type":"tag","tag":"OrganizerTag/party","display_name":"party","prefix":"OrganizerTag"},{"_type":"tag","tag":"OrganizerTag/fun","display_name":"fun","prefix":"OrganizerTag"},{"_type":"tag","tag":"OrganizerTag/pune","display_name":"pune","prefix":"OrganizerTag"},{"_type":"tag","tag":"OrganizerTag/puneevents","display_name":"puneevents","prefix":"OrganizerTag"},{"_type":"tag","tag":"OrganizerTag/june25","display_name":"june25","prefix":"OrganizerTag"},{"_type":"tag","tag":"OrganizerTag/kickazz","display_name":"kickazz","prefix":"OrganizerTag"},{"_type":"tag","tag":"OrganizerTag/streetmeetup","display_name":"streetmeetup","prefix":"OrganizerTag"},{"_type":"tag","tag":"OrganizerTag/koregaonpark","display_name":"koregaonpark","prefix":"OrganizerTag"},{"_type":"tag","tag":"OrganizerTag/punecommunityparties","display_name":"punecommunityparties","prefix":"OrganizerTag"}],"eventbrite_event_id":"654073991917","start_time":"18:00","primary_venue":{"_type":"destination_venue","name":"Koregaon Park","venue_profile_id":null,"address":{"city":"Pune","country":"IN","region":"MH","longitude":"73.8939748","localized_address_display":"Koregaon Park, Pune, MH 411001","postal_code":"411001","address_1":"Koregaon Park","address_2":"","latitude":"18.5362084","localized_multi_line_address_display":["Koregaon Park","Pune, MH 411001"],"localized_area_display":"Pune, MH"},"venue_profile_url":"","id":"158702679"},"primary_organizer":{"_type":"destination_profile","num_upcoming_events":null,"name":"Kickazz","profile_type":"organizer","num_followers":null,"url":"https://www.eventbrite.com/o/kickazz-67027781943","twitter":null,"summary":null,"num_saves":null,"image_id":null,"followed_by_you":false,"facebook":null,"num_collections":null,"id":"67027781943","website_url":null,"num_following":null},"series_id":null,"image_id":"532135979","is_protected_event":false,"is_cancelled":null,"primary_venue_id":"158702679","checkout_flow":"widget","name":"Street Meetup at Koregaon Park on 25th June - Pune by KickAzz","language":"en-us","url":"https://www.eventbrite.com/e/street-meetup-at-koregaon-park-on-25th-june-pune-by-kickazz-tickets-654073991917","hide_start_date":false,"summary":"An invite-only, innovative meetup of only 30 individuals to meet new friends and experience street life together.","is_online_event":false,"eid":"ehczqqhz","published":"2023-06-08T16:53:27Z"}]}